{
  "employees": [
    {
      "id": "1",
      "firstName": "Mutungi",
      "lastName": "Ambrozio",
      "email": "mutungi@gmail.com",
      "dob": "1999-07-29T21:00:00.000Z",
      "gender": "male",
      "education": "Masters",
      "company": "Google",
      "experience": 5,
      "salary": 260000
    },
    {
      "id": "2",
      "firstName": "Lovis",
      "lastName": "Ambrose",
      "email": "lovis@gmail.com",
      "dob": "1999-06-16T21:00:00.000Z",
      "gender": "male",
      "education": "Graduate",
      "company": "Microsoft",
      "experience": 5,
      "salary": 220000
    },
    {
      "id": "3",
      "firstName": "Muhanguzi",
      "lastName": "Arnold",
      "email": "arnold@gmail.com",
      "dob": "1999-07-22T21:00:00.000Z",
      "gender": "male",
      "education": "Diploma",
      "company": "Facebook",
      "experience": 3,
      "salary": 23000
    },
    {
      "firstName": "Mukama",
      "lastName": "Joseph",
      "email": "mukama@gmail.com",
      "dob": "1993-03-10T21:00:00.000Z",
      "gender": "other",
      "education": "Masters",
      "company": "big company",
      "experience": 4,
      "salary": 70000,
      "id": "4"
    },
    {
      "firstName": "Muhozi",
      "lastName": "James",
      "email": "james@gmail.com",
      "dob": "1992-06-10T21:00:00.000Z",
      "gender": "male",
      "education": "Diploma",
      "company": "Small Company",
      "experience": 4,
      "salary": 322200,
      "id": "5"
    },
    {
      "id": "6",
      "firstName": "xx",
      "lastName": "ccc",
      "email": "vvv",
      "dob": "2024-05-29T21:00:00.000Z",
      "gender": "male",
      "education": "Undergraduate",
      "company": "dd",
      "experience": 2,
      "salary": 333333
    },
    {
      "id": "7",
      "firstName": "",
      "lastName": "",
      "email": "",
      "dob": "",
      "gender": "",
      "education": "",
      "company": "",
      "experience": "",
      "salary": ""
    }
  ]
}